gtk_gtasks/__init__.py
gtk_gtasks/icon.png
gtk_gtasks/install.py
gtk_gtasks/main.py
gtk_gtasks/version.py
gtk_gtasks-0.0.1.dist-info/entry_points.txt
gtk_gtasks-0.0.1.dist-info/LICENSE
gtk_gtasks-0.0.1.dist-info/WHEEL
gtk_gtasks-0.0.1.dist-info/METADATA
gtk_gtasks-0.0.1.dist-info/RECORD
