Metadata-Version: 2.1
Name: gtk_gtasks
Version: 0.0.1
Summary: GTK Google Tasks
Author-email: Jacopo antipatico Scannella <code@bootkit.dev>
Classifier: License :: OSI Approved :: MIT License
Requires-Dist: PyGObject~=3.42.2
Project-URL: Github, https://github.com/antipatico/gtk_gtasks
Project-URL: Home, https://github.com/antipatico/gtk_gtasks
Project-URL: Issues, https://github.com/antipatico/gtk_gtasks/issues
